mss/__init__.py
mss/__main__.py
mss/base.py
mss/darwin.py
mss/exception.py
mss/factory.py
mss/linux.py
mss/models.py
mss/py.typed
mss/screenshot.py
mss/tools.py
mss/windows.py
mss-9.0.0.dist-info/METADATA
mss-9.0.0.dist-info/WHEEL
mss-9.0.0.dist-info/entry_points.txt
mss-9.0.0.dist-info/top_level.txt
mss-9.0.0.dist-info/RECORD
