Metadata-Version: 2.1
Name: mss
Version: 9.0.0
Summary: An ultra fast cross-platform multiple screenshots module in pure python using ctypes.
Home-page: https://github.com/BoboTiG/python-mss
Author: Mickaël 'Tiger-222' Schoentgen
Author-email: contact@tiger-222.fr
License: MIT
Project-URL: Documentation, https://python-mss.readthedocs.io
Project-URL: Source, https://github.com/BoboTiG/python-mss
Project-URL: Tracker, https://github.com/BoboTiG/python-mss/issues
Keywords: screen,screenshot,screencapture,screengrab
Platform: Darwin
Platform: Linux
Platform: Windows
Classifier: Development Status :: 5 - Production/Stable
Classifier: Environment :: MacOS X
Classifier: Intended Audience :: Developers
Classifier: Intended Audience :: Education
Classifier: Intended Audience :: End Users/Desktop
Classifier: Intended Audience :: Information Technology
Classifier: Intended Audience :: Science/Research
Classifier: License :: OSI Approved :: MIT License
Classifier: Operating System :: MacOS
Classifier: Operating System :: Microsoft :: Windows
Classifier: Operating System :: Unix
Classifier: Programming Language :: Python :: Implementation :: CPython
Classifier: Programming Language :: Python :: Implementation :: PyPy
Classifier: Programming Language :: Python
Classifier: Programming Language :: Python :: 3
Classifier: Programming Language :: Python :: 3 :: Only
Classifier: Programming Language :: Python :: 3.8
Classifier: Programming Language :: Python :: 3.9
Classifier: Programming Language :: Python :: 3.10
Classifier: Programming Language :: Python :: 3.11
Classifier: Programming Language :: Python :: 3.12
Classifier: Topic :: Multimedia :: Graphics :: Capture :: Screen Capture
Classifier: Topic :: Software Development :: Libraries
Requires-Python: >=3.8
